{
  "pageId": "WEN_02",
  "items": [
    {
      "text": "经过层层探寻，你已经把握了《马说》的意蕴，结合全文内容，完成最后的感悟理解。",
      "quiz": {
        "question_id": "WEN_02_C1",
        "module": "C",
        "question_type": "radio",
        "question_text": "本文以马喻人、托物寓意，全文寄托的核心情感是（）",
        "options": [
          "赞美千里马驰骋千里的矫健身姿",
          "批判养马人喂养马匹不够用心细致",
          "抒发怀才不遇的愤懑，批判统治者不识人才、埋没人才的愚昧",
          "感叹世间千里马数量稀少、弥足珍贵"
        ],
        "correct_answer": 2,
        "explanation": "正确选项：C。作者借千里马被埋没的悲惨遭遇，映射古代贤才不被重用、惨遭埋没的社会现实，对封建统治者不知人、埋没人才的现象进行了有力的揭露。抒发自身怀才不遇的不平之气，期盼自己的才能被发现，表达识才、惜才与用才的道理。",
        "difficulty": "L1"
      }
    }
  ]
}
